globus_sdk/__init__.py
globus_sdk/__init__.pyi
globus_sdk/_missing.py
globus_sdk/_payload.py
globus_sdk/client.py
globus_sdk/py.typed
globus_sdk/response.py
globus_sdk/_internal/__init__.py
globus_sdk/_internal/classprop.py
globus_sdk/_internal/guards.py
globus_sdk/_internal/lazy_import.py
globus_sdk/_internal/remarshal.py
globus_sdk/_internal/serializable.py
globus_sdk/_internal/type_definitions.py
globus_sdk/_internal/utils.py
globus_sdk/_internal/extensions/__init__.py
globus_sdk/_internal/extensions/globus_sdk_flake8.py
globus_sdk/_internal/extensions/sphinxext/__init__.py
globus_sdk/_internal/extensions/sphinxext/autodoc_hooks.py
globus_sdk/_internal/extensions/sphinxext/roles.py
globus_sdk/_internal/extensions/sphinxext/utils.py
globus_sdk/_internal/extensions/sphinxext/directives/__init__.py
globus_sdk/_internal/extensions/sphinxext/directives/add_content_directive.py
globus_sdk/_internal/extensions/sphinxext/directives/automethodlist.py
globus_sdk/_internal/extensions/sphinxext/directives/copy_params.py
globus_sdk/_internal/extensions/sphinxext/directives/enumerate_testing_fixtures.py
globus_sdk/_internal/extensions/sphinxext/directives/expand_testing_fixture.py
globus_sdk/_internal/extensions/sphinxext/directives/externaldoclink.py
globus_sdk/_internal/extensions/sphinxext/directives/list_known_scopes.py
globus_sdk/_internal/extensions/sphinxext/directives/paginated_usage.py
globus_sdk/authorizers/__init__.py
globus_sdk/authorizers/access_token.py
globus_sdk/authorizers/base.py
globus_sdk/authorizers/basic.py
globus_sdk/authorizers/client_credentials.py
globus_sdk/authorizers/refresh_token.py
globus_sdk/authorizers/renewing.py
globus_sdk/config/__init__.py
globus_sdk/config/env_vars.py
globus_sdk/config/environments.py
globus_sdk/exc/__init__.py
globus_sdk/exc/api.py
globus_sdk/exc/base.py
globus_sdk/exc/convert.py
globus_sdk/exc/err_info.py
globus_sdk/exc/warnings.py
globus_sdk/experimental/__init__.py
globus_sdk/gare/__init__.py
globus_sdk-4.3.0.dist-info/licenses/LICENSE
globus_sdk-4.3.0.dist-info/METADATA
globus_sdk-4.3.0.dist-info/WHEEL
globus_sdk-4.3.0.dist-info/top_level.txt
globus_sdk-4.3.0.dist-info/RECORD
