Metadata-Version: 2.4
Name: globus-sdk
Version: 4.3.0
Summary: Globus SDK for Python
Author-email: Globus Team <support@globus.org>
License: Apache-2.0
Project-URL: Homepage, https://github.com/globus/globus-sdk-python
Keywords: globus
Classifier: Development Status :: 5 - Production/Stable
Classifier: Intended Audience :: Developers
Classifier: License :: OSI Approved :: Apache Software License
Classifier: Programming Language :: Python
Classifier: Programming Language :: Python :: 3.9
Classifier: Programming Language :: Python :: 3.10
Classifier: Programming Language :: Python :: 3.11
Classifier: Programming Language :: Python :: 3.12
Classifier: Programming Language :: Python :: 3.13
Classifier: Programming Language :: Python :: 3.14
Requires-Python: >=3.9
License-File: LICENSE
Requires-Dist: requests<3.0.0,>=2.19.1
Requires-Dist: pyjwt[crypto]<3.0.0,>=2.0.0
Requires-Dist: cryptography!=3.4.0,>=3.3.1
Requires-Dist: typing_extensions>=4.0; python_version < "3.11"
Requires-Dist: importlib_resources>=5.12.0; python_version < "3.9"
Dynamic: license-file
